{
  "name": "Chuul",
  "tags": [
    "large",
    "aberration",
    "cr4",
    "monster-manual"
  ],
  "size": "Large",
  "type": "aberration",
  "alignment": "chaotic evil",
  "cr": "4 (1,100 XP)",
  "hp": "93 (11d10+33)",
  "ac": "16 (natural armor)",
  "speed": "30 ft., swim 30 ft.",
  "skills": "Perception +4",
  "immunities": "poison",
  "conimmunities": "poisoned",
  "senses": "darkvision 60 ft.",
  "languages": "understands Deep Speech but can't speak",
  "abilities": {
    "str": 19,
    "dex": 10,
    "con": 16,
    "int": 5,
    "wis": 11,
    "cha": 5
  },
  "traits": [
    {
      "name": "Amphibious",
      "desc": "The chuul can breathe air and water."
    },
    {
      "name": "Sense Magic",
      "desc": "The chuul senses magic within 120 feet of it at will. This trait otherwise works like the detect magic spell but isn't itself magical."
    }
  ],
  "actions": [
    {
      "name": "Multiattack",
      "desc": "The chuul makes two pincer attacks. If the chuul is grappling a creature, the chuul can also use its tentacles once."
    },
    {
      "name": "Pincer",
      "desc": "Melee Weapon Attack: +6 to hit, reach 10 ft., one target. Hit: 11 (2d6 + 4) bludgeoning damage. The target is grappled (escape DC 14) if it is a Large or smaller creature and the chuul doesn't have two other creatures grappled."
    },
    {
      "name": "Tentacles",
      "desc": "One creature grappled by the chuul must succeed on a DC 13 Constitution saving throw or be poisoned for 1 minute. Until this poison ends, the target is paralyzed. The target can repeat the saving throw at the end of each of its turns, ending the effect on itself on a success."
    }
  ]
}