{
  "name": "Gorgon",
  "tags": [
    "large",
    "monstrosity",
    "cr5",
    "monster-manual"
  ],
  "size": "Large",
  "type": "monstrosity",
  "alignment": "unaligned",
  "cr": "5 (1,800 XP)",
  "hp": "114 (12d10+48)",
  "ac": "19 (natural armor)",
  "speed": "40 ft.",
  "skills": "Perception +4",
  "immunities": "petrified",
  "senses": "darkvision 60 ft.",
  "abilities": {
    "str": 20,
    "dex": 11,
    "con": 18,
    "int": 2,
    "wis": 12,
    "cha": 7
  },
  "traits": [
    {
      "name": "Trampling Charge",
      "desc": "If the gorgon moves at least 20 feet straight toward a creature and then hits it with a gore attack on the same turn, that target must succeed on a DC 16 Strength saving throw or be knocked prone. If the target is prone, the gorgon can make one attack with its hooves against it as a bonus action."
    }
  ],
  "actions": [
    {
      "name": "Gore",
      "desc": "Melee Weapon Attack: +8 to hit, reach 5 ft., one target. Hit: 18 (2d12 + 5) piercing damage."
    },
    {
      "name": "Hooves",
      "desc": "Melee Weapon Attack: +8 to hit, reach 5 ft., one target. Hit: 16 (2d10 + 5) bludgeoning damage."
    },
    {
      "name": "Petrifying Breath (Recharge 5-6)",
      "desc": "The gorgon exhales petrifying gas in a 30-foot cone. Each creature in that area must succeed on a DC 13 Constitution saving throw. On a failed save, a target begins to turn to stone and is restrained. The restrained target must repeat the saving throw at the end of its next turn. On a success, the effect ends on the target. On a failure, the target is petrified until freed by the greater restoration spell or other magic."
    }
  ]
}