{
  "name": "Monarchon",
  "tags": [
    "medium",
    "fey",
    "cr7",
    "strongholds-and-followers"
  ],
  "size": "Medium",
  "type": "fey",
  "alignment": "chaotic neutral",
  "cr": "7 (2,900 XP)",
  "hp": "110 (13d10 + 39)",
  "ac": "17 (natural armor)",
  "speed": "30 ft., fly 30 ft. (hover)",
  "saves": "Wis +7, Cha +5",
  "skills": "History +4, Insight +7, Medicine +7, Nature +4, Perception + 6, Religion +4",
  "senses": "passive Perception 20",
  "languages": "Common, Elven, Sylvan",
  "abilities": {
    "str": 11,
    "dex": 15,
    "con": 16,
    "int": 12,
    "wis": 19,
    "cha": 14
  },
  "traits": [
    {
      "name": "Fey Ancestry",
      "desc": "Magic cannot put the Monarchon to sleep."
    },
    {
      "name": "Magic Resistance",
      "desc": "The Monarchon has advantage on saving throws against spells and other magical effects."
    },
    {
      "name": "Command Fey",
      "desc": "As a member of the Court of Arcadia, the Monarchon can cast <i>dominate monster</i> (DC 15) at will on any fey creature or elf."
    },
    {
      "name": "Innate Spellcasting",
      "desc": "The Monarchon\u2019s innate spellcasting ability is Wisdom (spell save DC 15). The Monarchon can innately cast the following spells, requiring no material components: * At will: <i>enthrall, sleep</i>"
    },
    {
      "name": "Spellcasting",
      "desc": "The Monarchon is a 7th-level spellcaster. Her spellcasting ability is Wisdom (spell save DC 15, +7 to hit with spell attacks). The Monarchon has the following cleric spells prepared: * Cantrips (at will): <i>guidance, sacred flame</i> * 1st level (4 slots): <i>bane, bless, command</i> * 2nd level (3 slots): <i>hold person, zone of truth</i> * 3rd level (3 slots): <i>dispel magic, revivify</i> * 4th level (1 slot): <i>banishment, death ward</i>"
    }
  ],
  "actions": [
    {
      "name": "Withering Touch",
      "desc": "Melee Spell Attack: +7 to hit, reach 5 ft., one creature. Hit: 15 (2d10 + 4) necrotic damage."
    },
    {
      "name": "Hypnotic Display",
      "desc": "The Monarchon spreads her wings and their false eyes pulsate with a rainbow of colors, targeting one creature she can see within 30 feet. If the target can see the Monarchon, the target must succeed on a DC 15 Wisdom saving throw against this magic or be charmed until the end of the Monarchon\u2019s next turn. The charmed target is stunned. If the target\u2019s saving throw is successful, the target is immune to the Monarchon\u2019s gaze for 24 hours."
    }
  ]
}